changes/__init__.py
changes/__main__.py
changes/attributes.py
changes/changelog.py
changes/cli.py
changes/compat.py
changes/config.py
changes/exceptions.py
changes/flow.py
changes/packaging.py
changes/probe.py
changes/shell.py
changes/util.py
changes/vcs.py
changes/venv.py
changes/verification.py
changes/version.py
changes-0.7.0.dist-info/DESCRIPTION.rst
changes-0.7.0.dist-info/entry_points.txt
changes-0.7.0.dist-info/METADATA
changes-0.7.0.dist-info/metadata.json
changes-0.7.0.dist-info/RECORD
changes-0.7.0.dist-info/top_level.txt
changes-0.7.0.dist-info/WHEEL
