Metadata-Version: 2.0
Name: changes
Version: 0.7.0
Summary: Generates a github changelog, tags and uploads your python library
Home-page: https://github.com/michaeljoseph/changes
Author: Michael Joseph
Author-email: michaeljoseph@gmail.com
License: The MIT License (MIT)
Requires-Dist: PyYAML (<4.0.0)
Requires-Dist: plumbum (<1.5.0)
Requires-Dist: click (<4.0.0)
Requires-Dist: giturlparse.py (<0.1.0)
Requires-Dist: future (<1.0.0)
Requires-Dist: path.py (<5.0.0)
Requires-Dist: python-magic (<0.5.0)
Requires-Dist: requests (<2.5.0)
Requires-Dist: semantic-version (<3.0.0)
Requires-Dist: uritemplate (<1.0.0)
Requires-Dist: twine (<1.4.0)
Requires-Dist: wheel (<1.0.0)
